django_pretty_response/middleware.py
django_pretty_response-1.0.2.dist-info/LICENSE
django_pretty_response-1.0.2.dist-info/METADATA
django_pretty_response-1.0.2.dist-info/WHEEL
django_pretty_response-1.0.2.dist-info/RECORD
