Metadata-Version: 2.1
Name: django-pretty-response
Version: 1.0.2
Summary: A middleware in Django that creates clean-formatted responses.
Home-page: https://github.com/knnarro/django-pretty-response
License: MIT
Keywords: django,middleware
Author: Naro
Author-email: knnarro@gmail.com
Requires-Python: >=3.8,<4.0
Classifier: License :: OSI Approved :: MIT License
Classifier: Programming Language :: Python :: 3
Classifier: Programming Language :: Python :: 3.8
Classifier: Programming Language :: Python :: 3.9
Classifier: Programming Language :: Python :: 3.10
Classifier: Programming Language :: Python :: 3.11
Classifier: Programming Language :: Python :: 3.12
Requires-Dist: django (>=3.2,<4.0)
Requires-Dist: djangorestframework (>=3.13.0,<4.0.0)
Project-URL: Repository, https://github.com/knnarro/django-pretty-response
